dynamixel_client/__init__.py
dynamixel_client/bus.py
dynamixel_client/main.py
dynamixel_client-0.1.dist-info/METADATA
dynamixel_client-0.1.dist-info/WHEEL
dynamixel_client-0.1.dist-info/entry_points.txt
dynamixel_client-0.1.dist-info/RECORD
