Metadata-Version: 2.3
Name: dynamixel-client
Version: 0.1
Summary: Dora Node client for dynamixel motors.
License: MIT
Author: Hennzau
Author-email: <dev@enzo-le-van.fr>
Requires-Python: >=3.9
Classifier: License :: OSI Approved :: MIT License
Classifier: Programming Language :: Python :: 3
Classifier: Programming Language :: Python :: 3.9
Classifier: Programming Language :: Python :: 3.10
Classifier: Programming Language :: Python :: 3.11
Classifier: Programming Language :: Python :: 3.12
Classifier: Programming Language :: Python :: 3.13
Requires-Dist: dora-rs (==0.3.5)
Requires-Dist: dynamixel-sdk (==3.7.31)
